mrarbgrad
