Metadata-Version: 2.4
Name: MRArbGrad
Version: 4.2.0
Summary: Gradient waveform design tool for arbitrary k-space trajectories.
Author-email: Ryan <ryan_shanghaitech@proton.me>
License-Expression: MIT
Project-URL: Repository, https://github.com/RyanShanghaitech/MRArbGrad
Project-URL: Examples, https://github.com/RyanShanghaitech/MRArbGrad/tree/main/example
Keywords: mri,pulse-sequence,gradient-waveform,non-Cartesian,real-time
License-File: LICENSE
Requires-Dist: numpy
Dynamic: license-file
